polaritymodel/__init__.py
polaritymodel/convert_save_format.py
polaritymodel/initsystems.py
polaritymodel/polarcore.py
polaritymodel/polargrid.py
polaritymodel/potentials.py
polaritymodel/potentials_wnt.py
polaritymodel/plot/__init__.py
polaritymodel/plot/animate.py
polaritymodel/plot/animate_ligand.py
polaritymodel/plot/animate_wnt.py
polaritymodel/plot/animate_wnt_skipframes.py
polaritymodel/plot/cones.py
polaritymodel/plot/cones_wnt.py
polaritymodel/plot/cones_wnt_ligand_grid.py
polaritymodel/plot/ligand_density_in_plane.py
polaritymodel/plot/ligand_density_in_plane_with_receptor.py
polaritymodel/plot/ligand_density_pde.py
polaritymodel/plot/ligand_density_pde_with_cells.py
polaritymodel/plot/plotcore.py
polaritymodel-0.1.2.dist-info/LICENSE
polaritymodel-0.1.2.dist-info/METADATA
polaritymodel-0.1.2.dist-info/WHEEL
polaritymodel-0.1.2.dist-info/top_level.txt
polaritymodel-0.1.2.dist-info/RECORD
