Metadata-Version: 2.1
Name: polaritymodel
Version: 0.1.2
Summary: A package for running the cell polarity model
Home-page: https://github.com/jasnyder/polarpkg
Author: Jordan Snyder
Author-email: snydrew@gmail.com
Classifier: Programming Language :: Python :: 3
Classifier: License :: OSI Approved :: MIT License
Classifier: Operating System :: OS Independent
Requires-Python: >=3.6
License-File: LICENSE
Requires-Dist: torch
Requires-Dist: torchaudio
Requires-Dist: torchvision
Requires-Dist: numpy
Requires-Dist: scipy
Requires-Dist: plotly
Requires-Dist: pandas
